tartiflette_request_context_hooks/__init__.py
tartiflette_request_context_hooks/base_request_context_hooks.py
tartiflette_request_context_hooks/request_context_hooks.py
tartiflette_request_context_hooks-2.0.0.dist-info/LICENSE
tartiflette_request_context_hooks-2.0.0.dist-info/METADATA
tartiflette_request_context_hooks-2.0.0.dist-info/WHEEL
tartiflette_request_context_hooks-2.0.0.dist-info/top_level.txt
tartiflette_request_context_hooks-2.0.0.dist-info/RECORD
