Metadata-Version: 2.1
Name: tartiflette-request-context-hooks
Version: 2.0.0
Summary: DEPRECATED: Framework for tartiflette request/resolver context data assignment - use tartiflette-middleware instead
Home-page: https://github.com/daveoconnor/tartiflette-request-context-hooks
Author: Dave O'Connor
Author-email: github@dead-pixels.org
License: UNKNOWN
Platform: UNKNOWN
Classifier: Programming Language :: Python :: 3
Classifier: License :: OSI Approved :: MIT License
Classifier: Operating System :: OS Independent
Requires-Python: >=3.8
Requires-Dist: tartiflette (>=1.2)
